MANIFEST.in
setup.py
recast_resultblueprints.egg-info/PKG-INFO
recast_resultblueprints.egg-info/SOURCES.txt
recast_resultblueprints.egg-info/dependency_links.txt
recast_resultblueprints.egg-info/requires.txt
recast_resultblueprints.egg-info/top_level.txt
recastresultblueprints/__init__.py
recastresultblueprints/__init__.pyc
recastresultblueprints/yadage_result/__init__.py
recastresultblueprints/yadage_result/__init__.pyc
recastresultblueprints/yadage_result/blueprint.py
recastresultblueprints/yadage_result/blueprint.pyc
recastresultblueprints/yadage_result/templates/recast_result.html