Metadata-Version: 1.0
Name: recast-resultblueprints
Version: 0.0.1
Summary: recast-resultblueprints
Home-page: http://github.com/recast-hep/recast-resultblueprints
Author: Lukas Heinrich
Author-email: lukas.heinrich@cern.ch
License: UNKNOWN
Platform: UNKNOWN
